{
  "KIA": {
    "games": 127,
    "wins": 59,
    "losses": 64,
    "draws": 4,
    "runs_scored": 611,
    "runs_allowed": 633,
    "win_rate": "0.480",
    "run_diff": -22
  },
  "LG": {
    "games": 131,
    "wins": 79,
    "losses": 49,
    "draws": 3,
    "runs_scored": 705,
    "runs_allowed": 518,
    "win_rate": "0.617",
    "run_diff": 187
  },
  "삼성": {
    "games": 131,
    "wins": 65,
    "losses": 64,
    "draws": 2,
    "runs_scored": 679,
    "runs_allowed": 587,
    "win_rate": "0.504",
    "run_diff": 92
  },
  "두산": {
    "games": 129,
    "wins": 56,
    "losses": 67,
    "draws": 6,
    "runs_scored": 592,
    "runs_allowed": 617,
    "win_rate": "0.455",
    "run_diff": -25
  },
  "KT": {
    "games": 131,
    "wins": 65,
    "losses": 62,
    "draws": 4,
    "runs_scored": 584,
    "runs_allowed": 589,
    "win_rate": "0.512",
    "run_diff": -5
  },
  "SSG": {
    "games": 129,
    "wins": 66,
    "losses": 59,
    "draws": 4,
    "runs_scored": 533,
    "runs_allowed": 505,
    "win_rate": "0.528",
    "run_diff": 28
  },
  "롯데": {
    "games": 132,
    "wins": 62,
    "losses": 64,
    "draws": 6,
    "runs_scored": 611,
    "runs_allowed": 666,
    "win_rate": "0.492",
    "run_diff": -55
  },
  "한화": {
    "games": 130,
    "wins": 75,
    "losses": 52,
    "draws": 3,
    "runs_scored": 614,
    "runs_allowed": 488,
    "win_rate": "0.591",
    "run_diff": 126
  },
  "NC": {
    "games": 128,
    "wins": 59,
    "losses": 63,
    "draws": 6,
    "runs_scored": 640,
    "runs_allowed": 697,
    "win_rate": "0.484",
    "run_diff": -57
  },
  "키움": {
    "games": 132,
    "wins": 43,
    "losses": 85,
    "draws": 4,
    "runs_scored": 524,
    "runs_allowed": 793,
    "win_rate": "0.336",
    "run_diff": -269
  }
}