{
  "lastUpdated": "2025-09-13T05:10:43.722Z",
  "updateDate": "2025. 9. 13.",
  "note": "2025-season-data-clean.txt 기반 완전 자동화 처리",
  "totalData": {
    "한화": {
      "LG": {
        "wins": 15,
        "losses": 21,
        "draws": 3,
        "homeWins": 9,
        "homeLosses": 0,
        "homeDraws": 3,
        "awayWins": 6,
        "awayLosses": 21,
        "awayDraws": 0
      },
      "롯데": {
        "wins": 36,
        "losses": 18,
        "draws": 3,
        "homeWins": 15,
        "homeLosses": 9,
        "homeDraws": 0,
        "awayWins": 21,
        "awayLosses": 9,
        "awayDraws": 3
      },
      "SSG": {
        "wins": 30,
        "losses": 21,
        "draws": 0,
        "homeWins": 12,
        "homeLosses": 15,
        "homeDraws": 0,
        "awayWins": 18,
        "awayLosses": 6,
        "awayDraws": 0
      },
      "KT": {
        "wins": 27,
        "losses": 15,
        "draws": 0,
        "homeWins": 15,
        "homeLosses": 12,
        "homeDraws": 0,
        "awayWins": 12,
        "awayLosses": 3,
        "awayDraws": 0
      },
      "KIA": {
        "wins": 30,
        "losses": 12,
        "draws": 0,
        "homeWins": 21,
        "homeLosses": 3,
        "homeDraws": 0,
        "awayWins": 9,
        "awayLosses": 9,
        "awayDraws": 0
      },
      "삼성": {
        "wins": 30,
        "losses": 27,
        "draws": 0,
        "homeWins": 18,
        "homeLosses": 12,
        "homeDraws": 0,
        "awayWins": 12,
        "awayLosses": 15,
        "awayDraws": 0
      },
      "NC": {
        "wins": 33,
        "losses": 18,
        "draws": 3,
        "homeWins": 18,
        "homeLosses": 3,
        "homeDraws": 3,
        "awayWins": 15,
        "awayLosses": 15,
        "awayDraws": 0
      },
      "두산": {
        "wins": 18,
        "losses": 30,
        "draws": 3,
        "homeWins": 9,
        "homeLosses": 24,
        "homeDraws": 0,
        "awayWins": 9,
        "awayLosses": 6,
        "awayDraws": 3
      },
      "키움": {
        "wins": 36,
        "losses": 3,
        "draws": 0,
        "homeWins": 9,
        "homeLosses": 3,
        "homeDraws": 0,
        "awayWins": 27,
        "awayLosses": 0,
        "awayDraws": 0
      }
    },
    "LG": {
      "한화": {
        "wins": 21,
        "losses": 15,
        "draws": 3,
        "homeWins": 21,
        "homeLosses": 6,
        "homeDraws": 0,
        "awayWins": 0,
        "awayLosses": 9,
        "awayDraws": 3
      },
      "롯데": {
        "wins": 33,
        "losses": 15,
        "draws": 6,
        "homeWins": 24,
        "homeLosses": 3,
        "homeDraws": 3,
        "awayWins": 9,
        "awayLosses": 12,
        "awayDraws": 3
      },
      "SSG": {
        "wins": 33,
        "losses": 24,
        "draws": 0,
        "homeWins": 12,
        "homeLosses": 12,
        "homeDraws": 0,
        "awayWins": 21,
        "awayLosses": 12,
        "awayDraws": 0
      },
      "KT": {
        "wins": 27,
        "losses": 24,
        "draws": 0,
        "homeWins": 12,
        "homeLosses": 12,
        "homeDraws": 0,
        "awayWins": 15,
        "awayLosses": 12,
        "awayDraws": 0
      },
      "KIA": {
        "wins": 30,
        "losses": 12,
        "draws": 0,
        "homeWins": 9,
        "homeLosses": 6,
        "homeDraws": 0,
        "awayWins": 21,
        "awayLosses": 6,
        "awayDraws": 0
      },
      "삼성": {
        "wins": 30,
        "losses": 21,
        "draws": 0,
        "homeWins": 6,
        "homeLosses": 12,
        "homeDraws": 0,
        "awayWins": 24,
        "awayLosses": 9,
        "awayDraws": 0
      },
      "NC": {
        "wins": 27,
        "losses": 18,
        "draws": 0,
        "homeWins": 9,
        "homeLosses": 12,
        "homeDraws": 0,
        "awayWins": 18,
        "awayLosses": 6,
        "awayDraws": 0
      },
      "두산": {
        "wins": 30,
        "losses": 18,
        "draws": 0,
        "homeWins": 15,
        "homeLosses": 9,
        "homeDraws": 0,
        "awayWins": 15,
        "awayLosses": 9,
        "awayDraws": 0
      },
      "키움": {
        "wins": 27,
        "losses": 24,
        "draws": 0,
        "homeWins": 18,
        "homeLosses": 9,
        "homeDraws": 0,
        "awayWins": 9,
        "awayLosses": 15,
        "awayDraws": 0
      }
    },
    "롯데": {
      "한화": {
        "wins": 18,
        "losses": 36,
        "draws": 3,
        "homeWins": 9,
        "homeLosses": 21,
        "homeDraws": 3,
        "awayWins": 9,
        "awayLosses": 15,
        "awayDraws": 0
      },
      "LG": {
        "wins": 15,
        "losses": 33,
        "draws": 6,
        "homeWins": 12,
        "homeLosses": 9,
        "homeDraws": 3,
        "awayWins": 3,
        "awayLosses": 24,
        "awayDraws": 3
      },
      "SSG": {
        "wins": 15,
        "losses": 30,
        "draws": 0,
        "homeWins": 9,
        "homeLosses": 15,
        "homeDraws": 0,
        "awayWins": 6,
        "awayLosses": 15,
        "awayDraws": 0
      },
      "KT": {
        "wins": 24,
        "losses": 21,
        "draws": 6,
        "homeWins": 12,
        "homeLosses": 12,
        "homeDraws": 3,
        "awayWins": 12,
        "awayLosses": 9,
        "awayDraws": 3
      },
      "KIA": {
        "wins": 30,
        "losses": 24,
        "draws": 3,
        "homeWins": 18,
        "homeLosses": 12,
        "homeDraws": 3,
        "awayWins": 12,
        "awayLosses": 12,
        "awayDraws": 0
      },
      "삼성": {
        "wins": 21,
        "losses": 15,
        "draws": 3,
        "homeWins": 15,
        "homeLosses": 6,
        "homeDraws": 3,
        "awayWins": 6,
        "awayLosses": 9,
        "awayDraws": 0
      },
      "NC": {
        "wins": 21,
        "losses": 21,
        "draws": 0,
        "homeWins": 9,
        "homeLosses": 9,
        "homeDraws": 0,
        "awayWins": 12,
        "awayLosses": 12,
        "awayDraws": 0
      },
      "두산": {
        "wins": 21,
        "losses": 21,
        "draws": 3,
        "homeWins": 9,
        "homeLosses": 15,
        "homeDraws": 3,
        "awayWins": 12,
        "awayLosses": 6,
        "awayDraws": 0
      },
      "키움": {
        "wins": 33,
        "losses": 18,
        "draws": 0,
        "homeWins": 12,
        "homeLosses": 6,
        "homeDraws": 0,
        "awayWins": 21,
        "awayLosses": 12,
        "awayDraws": 0
      }
    },
    "SSG": {
      "한화": {
        "wins": 21,
        "losses": 30,
        "draws": 0,
        "homeWins": 6,
        "homeLosses": 18,
        "homeDraws": 0,
        "awayWins": 15,
        "awayLosses": 12,
        "awayDraws": 0
      },
      "LG": {
        "wins": 24,
        "losses": 33,
        "draws": 0,
        "homeWins": 12,
        "homeLosses": 21,
        "homeDraws": 0,
        "awayWins": 12,
        "awayLosses": 12,
        "awayDraws": 0
      },
      "롯데": {
        "wins": 30,
        "losses": 15,
        "draws": 0,
        "homeWins": 15,
        "homeLosses": 6,
        "homeDraws": 0,
        "awayWins": 15,
        "awayLosses": 9,
        "awayDraws": 0
      },
      "KT": {
        "wins": 24,
        "losses": 18,
        "draws": 0,
        "homeWins": 9,
        "homeLosses": 6,
        "homeDraws": 0,
        "awayWins": 15,
        "awayLosses": 12,
        "awayDraws": 0
      },
      "KIA": {
        "wins": 21,
        "losses": 21,
        "draws": 3,
        "homeWins": 9,
        "homeLosses": 12,
        "homeDraws": 3,
        "awayWins": 12,
        "awayLosses": 9,
        "awayDraws": 0
      },
      "삼성": {
        "wins": 27,
        "losses": 27,
        "draws": 3,
        "homeWins": 12,
        "homeLosses": 12,
        "homeDraws": 3,
        "awayWins": 15,
        "awayLosses": 15,
        "awayDraws": 0
      },
      "NC": {
        "wins": 24,
        "losses": 15,
        "draws": 3,
        "homeWins": 18,
        "homeLosses": 6,
        "homeDraws": 3,
        "awayWins": 6,
        "awayLosses": 9,
        "awayDraws": 0
      },
      "두산": {
        "wins": 21,
        "losses": 15,
        "draws": 0,
        "homeWins": 6,
        "homeLosses": 6,
        "homeDraws": 0,
        "awayWins": 15,
        "awayLosses": 9,
        "awayDraws": 0
      },
      "키움": {
        "wins": 30,
        "losses": 21,
        "draws": 3,
        "homeWins": 21,
        "homeLosses": 12,
        "homeDraws": 3,
        "awayWins": 9,
        "awayLosses": 9,
        "awayDraws": 0
      }
    },
    "KT": {
      "한화": {
        "wins": 15,
        "losses": 27,
        "draws": 0,
        "homeWins": 3,
        "homeLosses": 12,
        "homeDraws": 0,
        "awayWins": 12,
        "awayLosses": 15,
        "awayDraws": 0
      },
      "LG": {
        "wins": 24,
        "losses": 27,
        "draws": 0,
        "homeWins": 12,
        "homeLosses": 15,
        "homeDraws": 0,
        "awayWins": 12,
        "awayLosses": 12,
        "awayDraws": 0
      },
      "롯데": {
        "wins": 21,
        "losses": 24,
        "draws": 6,
        "homeWins": 9,
        "homeLosses": 12,
        "homeDraws": 3,
        "awayWins": 12,
        "awayLosses": 12,
        "awayDraws": 3
      },
      "SSG": {
        "wins": 18,
        "losses": 24,
        "draws": 0,
        "homeWins": 12,
        "homeLosses": 15,
        "homeDraws": 0,
        "awayWins": 6,
        "awayLosses": 9,
        "awayDraws": 0
      },
      "KIA": {
        "wins": 21,
        "losses": 24,
        "draws": 0,
        "homeWins": 18,
        "homeLosses": 9,
        "homeDraws": 0,
        "awayWins": 3,
        "awayLosses": 15,
        "awayDraws": 0
      },
      "삼성": {
        "wins": 27,
        "losses": 12,
        "draws": 0,
        "homeWins": 18,
        "homeLosses": 6,
        "homeDraws": 0,
        "awayWins": 9,
        "awayLosses": 6,
        "awayDraws": 0
      },
      "NC": {
        "wins": 24,
        "losses": 27,
        "draws": 3,
        "homeWins": 9,
        "homeLosses": 21,
        "homeDraws": 0,
        "awayWins": 15,
        "awayLosses": 6,
        "awayDraws": 3
      },
      "두산": {
        "wins": 39,
        "losses": 12,
        "draws": 3,
        "homeWins": 21,
        "homeLosses": 6,
        "homeDraws": 0,
        "awayWins": 18,
        "awayLosses": 6,
        "awayDraws": 3
      },
      "키움": {
        "wins": 33,
        "losses": 18,
        "draws": 0,
        "homeWins": 15,
        "homeLosses": 9,
        "homeDraws": 0,
        "awayWins": 18,
        "awayLosses": 9,
        "awayDraws": 0
      }
    },
    "KIA": {
      "한화": {
        "wins": 12,
        "losses": 30,
        "draws": 0,
        "homeWins": 9,
        "homeLosses": 9,
        "homeDraws": 0,
        "awayWins": 3,
        "awayLosses": 21,
        "awayDraws": 0
      },
      "LG": {
        "wins": 12,
        "losses": 30,
        "draws": 0,
        "homeWins": 6,
        "homeLosses": 21,
        "homeDraws": 0,
        "awayWins": 6,
        "awayLosses": 9,
        "awayDraws": 0
      },
      "롯데": {
        "wins": 24,
        "losses": 30,
        "draws": 3,
        "homeWins": 12,
        "homeLosses": 12,
        "homeDraws": 0,
        "awayWins": 12,
        "awayLosses": 18,
        "awayDraws": 3
      },
      "SSG": {
        "wins": 21,
        "losses": 21,
        "draws": 3,
        "homeWins": 9,
        "homeLosses": 12,
        "homeDraws": 0,
        "awayWins": 12,
        "awayLosses": 9,
        "awayDraws": 3
      },
      "KT": {
        "wins": 24,
        "losses": 21,
        "draws": 0,
        "homeWins": 15,
        "homeLosses": 3,
        "homeDraws": 0,
        "awayWins": 9,
        "awayLosses": 18,
        "awayDraws": 0
      },
      "삼성": {
        "wins": 30,
        "losses": 21,
        "draws": 0,
        "homeWins": 18,
        "homeLosses": 9,
        "homeDraws": 0,
        "awayWins": 12,
        "awayLosses": 12,
        "awayDraws": 0
      },
      "NC": {
        "wins": 24,
        "losses": 24,
        "draws": 0,
        "homeWins": 9,
        "homeLosses": 6,
        "homeDraws": 0,
        "awayWins": 15,
        "awayLosses": 18,
        "awayDraws": 0
      },
      "두산": {
        "wins": 33,
        "losses": 18,
        "draws": 6,
        "homeWins": 18,
        "homeLosses": 3,
        "homeDraws": 3,
        "awayWins": 15,
        "awayLosses": 15,
        "awayDraws": 3
      },
      "키움": {
        "wins": 21,
        "losses": 18,
        "draws": 6,
        "homeWins": 12,
        "homeLosses": 12,
        "homeDraws": 3,
        "awayWins": 9,
        "awayLosses": 6,
        "awayDraws": 3
      }
    },
    "삼성": {
      "한화": {
        "wins": 27,
        "losses": 30,
        "draws": 0,
        "homeWins": 15,
        "homeLosses": 12,
        "homeDraws": 0,
        "awayWins": 12,
        "awayLosses": 18,
        "awayDraws": 0
      },
      "LG": {
        "wins": 21,
        "losses": 30,
        "draws": 0,
        "homeWins": 9,
        "homeLosses": 24,
        "homeDraws": 0,
        "awayWins": 12,
        "awayLosses": 6,
        "awayDraws": 0
      },
      "롯데": {
        "wins": 15,
        "losses": 21,
        "draws": 3,
        "homeWins": 9,
        "homeLosses": 6,
        "homeDraws": 0,
        "awayWins": 6,
        "awayLosses": 15,
        "awayDraws": 3
      },
      "SSG": {
        "wins": 27,
        "losses": 27,
        "draws": 3,
        "homeWins": 15,
        "homeLosses": 15,
        "homeDraws": 0,
        "awayWins": 12,
        "awayLosses": 12,
        "awayDraws": 3
      },
      "KT": {
        "wins": 12,
        "losses": 27,
        "draws": 0,
        "homeWins": 6,
        "homeLosses": 9,
        "homeDraws": 0,
        "awayWins": 6,
        "awayLosses": 18,
        "awayDraws": 0
      },
      "KIA": {
        "wins": 21,
        "losses": 30,
        "draws": 0,
        "homeWins": 12,
        "homeLosses": 12,
        "homeDraws": 0,
        "awayWins": 9,
        "awayLosses": 18,
        "awayDraws": 0
      },
      "NC": {
        "wins": 24,
        "losses": 21,
        "draws": 0,
        "homeWins": 18,
        "homeLosses": 9,
        "homeDraws": 0,
        "awayWins": 6,
        "awayLosses": 12,
        "awayDraws": 0
      },
      "두산": {
        "wins": 30,
        "losses": 21,
        "draws": 0,
        "homeWins": 12,
        "homeLosses": 12,
        "homeDraws": 0,
        "awayWins": 18,
        "awayLosses": 9,
        "awayDraws": 0
      },
      "키움": {
        "wins": 33,
        "losses": 15,
        "draws": 0,
        "homeWins": 24,
        "homeLosses": 6,
        "homeDraws": 0,
        "awayWins": 9,
        "awayLosses": 9,
        "awayDraws": 0
      }
    },
    "NC": {
      "한화": {
        "wins": 18,
        "losses": 33,
        "draws": 3,
        "homeWins": 15,
        "homeLosses": 15,
        "homeDraws": 0,
        "awayWins": 3,
        "awayLosses": 18,
        "awayDraws": 3
      },
      "LG": {
        "wins": 18,
        "losses": 27,
        "draws": 0,
        "homeWins": 6,
        "homeLosses": 18,
        "homeDraws": 0,
        "awayWins": 12,
        "awayLosses": 9,
        "awayDraws": 0
      },
      "롯데": {
        "wins": 21,
        "losses": 21,
        "draws": 0,
        "homeWins": 12,
        "homeLosses": 12,
        "homeDraws": 0,
        "awayWins": 9,
        "awayLosses": 9,
        "awayDraws": 0
      },
      "SSG": {
        "wins": 15,
        "losses": 24,
        "draws": 3,
        "homeWins": 9,
        "homeLosses": 6,
        "homeDraws": 0,
        "awayWins": 6,
        "awayLosses": 18,
        "awayDraws": 3
      },
      "KT": {
        "wins": 27,
        "losses": 24,
        "draws": 3,
        "homeWins": 6,
        "homeLosses": 15,
        "homeDraws": 3,
        "awayWins": 21,
        "awayLosses": 9,
        "awayDraws": 0
      },
      "KIA": {
        "wins": 24,
        "losses": 24,
        "draws": 0,
        "homeWins": 18,
        "homeLosses": 15,
        "homeDraws": 0,
        "awayWins": 6,
        "awayLosses": 9,
        "awayDraws": 0
      },
      "삼성": {
        "wins": 21,
        "losses": 24,
        "draws": 0,
        "homeWins": 12,
        "homeLosses": 6,
        "homeDraws": 0,
        "awayWins": 9,
        "awayLosses": 18,
        "awayDraws": 0
      },
      "두산": {
        "wins": 18,
        "losses": 21,
        "draws": 6,
        "homeWins": 6,
        "homeLosses": 15,
        "homeDraws": 0,
        "awayWins": 12,
        "awayLosses": 6,
        "awayDraws": 6
      },
      "키움": {
        "wins": 30,
        "losses": 24,
        "draws": 3,
        "homeWins": 18,
        "homeLosses": 15,
        "homeDraws": 0,
        "awayWins": 12,
        "awayLosses": 9,
        "awayDraws": 3
      }
    },
    "두산": {
      "한화": {
        "wins": 30,
        "losses": 18,
        "draws": 3,
        "homeWins": 6,
        "homeLosses": 9,
        "homeDraws": 3,
        "awayWins": 24,
        "awayLosses": 9,
        "awayDraws": 0
      },
      "LG": {
        "wins": 18,
        "losses": 30,
        "draws": 0,
        "homeWins": 9,
        "homeLosses": 15,
        "homeDraws": 0,
        "awayWins": 9,
        "awayLosses": 15,
        "awayDraws": 0
      },
      "롯데": {
        "wins": 21,
        "losses": 21,
        "draws": 3,
        "homeWins": 6,
        "homeLosses": 12,
        "homeDraws": 0,
        "awayWins": 15,
        "awayLosses": 9,
        "awayDraws": 3
      },
      "SSG": {
        "wins": 15,
        "losses": 21,
        "draws": 0,
        "homeWins": 9,
        "homeLosses": 15,
        "homeDraws": 0,
        "awayWins": 6,
        "awayLosses": 6,
        "awayDraws": 0
      },
      "KT": {
        "wins": 12,
        "losses": 39,
        "draws": 3,
        "homeWins": 6,
        "homeLosses": 18,
        "homeDraws": 3,
        "awayWins": 6,
        "awayLosses": 21,
        "awayDraws": 0
      },
      "KIA": {
        "wins": 18,
        "losses": 33,
        "draws": 6,
        "homeWins": 15,
        "homeLosses": 15,
        "homeDraws": 3,
        "awayWins": 3,
        "awayLosses": 18,
        "awayDraws": 3
      },
      "삼성": {
        "wins": 21,
        "losses": 30,
        "draws": 0,
        "homeWins": 9,
        "homeLosses": 18,
        "homeDraws": 0,
        "awayWins": 12,
        "awayLosses": 12,
        "awayDraws": 0
      },
      "NC": {
        "wins": 21,
        "losses": 18,
        "draws": 6,
        "homeWins": 6,
        "homeLosses": 12,
        "homeDraws": 6,
        "awayWins": 15,
        "awayLosses": 6,
        "awayDraws": 0
      },
      "키움": {
        "wins": 27,
        "losses": 15,
        "draws": 3,
        "homeWins": 12,
        "homeLosses": 0,
        "homeDraws": 0,
        "awayWins": 15,
        "awayLosses": 15,
        "awayDraws": 3
      }
    },
    "키움": {
      "한화": {
        "wins": 3,
        "losses": 36,
        "draws": 0,
        "homeWins": 0,
        "homeLosses": 27,
        "homeDraws": 0,
        "awayWins": 3,
        "awayLosses": 9,
        "awayDraws": 0
      },
      "LG": {
        "wins": 24,
        "losses": 27,
        "draws": 0,
        "homeWins": 15,
        "homeLosses": 9,
        "homeDraws": 0,
        "awayWins": 9,
        "awayLosses": 18,
        "awayDraws": 0
      },
      "롯데": {
        "wins": 18,
        "losses": 33,
        "draws": 0,
        "homeWins": 12,
        "homeLosses": 21,
        "homeDraws": 0,
        "awayWins": 6,
        "awayLosses": 12,
        "awayDraws": 0
      },
      "SSG": {
        "wins": 21,
        "losses": 30,
        "draws": 3,
        "homeWins": 9,
        "homeLosses": 9,
        "homeDraws": 0,
        "awayWins": 12,
        "awayLosses": 21,
        "awayDraws": 3
      },
      "KT": {
        "wins": 18,
        "losses": 33,
        "draws": 0,
        "homeWins": 9,
        "homeLosses": 18,
        "homeDraws": 0,
        "awayWins": 9,
        "awayLosses": 15,
        "awayDraws": 0
      },
      "KIA": {
        "wins": 18,
        "losses": 21,
        "draws": 6,
        "homeWins": 6,
        "homeLosses": 9,
        "homeDraws": 3,
        "awayWins": 12,
        "awayLosses": 12,
        "awayDraws": 3
      },
      "삼성": {
        "wins": 15,
        "losses": 33,
        "draws": 0,
        "homeWins": 9,
        "homeLosses": 9,
        "homeDraws": 0,
        "awayWins": 6,
        "awayLosses": 24,
        "awayDraws": 0
      },
      "NC": {
        "wins": 24,
        "losses": 30,
        "draws": 3,
        "homeWins": 9,
        "homeLosses": 12,
        "homeDraws": 3,
        "awayWins": 15,
        "awayLosses": 18,
        "awayDraws": 0
      },
      "두산": {
        "wins": 15,
        "losses": 27,
        "draws": 3,
        "homeWins": 15,
        "homeLosses": 15,
        "homeDraws": 3,
        "awayWins": 0,
        "awayLosses": 12,
        "awayDraws": 0
      }
    }
  },
  "source": "CLEAN_TXT_AUTOMATION",
  "dataDate": "2025-09-12"
}